cfg/__init__.py
cfg/get_config.py
jevgeni_tarassov_cfg-0.1.0.dist-info/LICENSE
jevgeni_tarassov_cfg-0.1.0.dist-info/METADATA
jevgeni_tarassov_cfg-0.1.0.dist-info/WHEEL
jevgeni_tarassov_cfg-0.1.0.dist-info/RECORD
