Metadata-Version: 2.1
Name: jevgeni-tarassov-cfg
Version: 0.1.0
Summary: 
Author: Jevgeni Tarassov
Author-email: jevgeni@tarassov.ch
Requires-Python: >=3.10,<4.0
Classifier: Programming Language :: Python :: 3
Classifier: Programming Language :: Python :: 3.10
Classifier: Programming Language :: Python :: 3.11
Requires-Dist: jevgeni-tarassov-rusty-results (>=1.0.0,<2.0.0)
Requires-Dist: python-dotenv (>=1.0.0,<2.0.0)
Requires-Dist: toml (>=0.10.2,<0.11.0)
